sldaCluster/LICENSE
sldaCluster/Main.py
sldaCluster/README.rst
sldaCluster/__init__.py
sldaCluster/requirements.txt
sldaCluster/settings.txt
sldaCluster/slda
sldaCluster/sldaModel.py
sldaCluster/stopwords_en.txt
sldaCluster/tfidf.py
sldaCluster/word2vec.py
sldaCluster-1.0.8.dist-info/METADATA
sldaCluster-1.0.8.dist-info/RECORD
sldaCluster-1.0.8.dist-info/WHEEL
sldaCluster-1.0.8.dist-info/top_level.txt
